fnet_import_parser/__init__.py
fnet_import_parser/cli/__init__.py
fnet_import_parser/cli/index.py
fnet_import_parser/lib/__init__.py
fnet_import_parser/lib/index.py
fnet_import_parser-0.1.11.dist-info/METADATA
fnet_import_parser-0.1.11.dist-info/WHEEL
fnet_import_parser-0.1.11.dist-info/entry_points.txt
fnet_import_parser-0.1.11.dist-info/top_level.txt
fnet_import_parser-0.1.11.dist-info/RECORD
